trustcaptcha/__init__.py
trustcaptcha/captcha_manager.py
trustcaptcha/model/__init__.py
trustcaptcha/model/verification_result.py
trustcaptcha/model/verification_token.py
trustcaptcha_python-1.2.1.dist-info/licenses/LICENSE.md
trustcaptcha_python-1.2.1.dist-info/METADATA
trustcaptcha_python-1.2.1.dist-info/WHEEL
trustcaptcha_python-1.2.1.dist-info/entry_points.txt
trustcaptcha_python-1.2.1.dist-info/top_level.txt
trustcaptcha_python-1.2.1.dist-info/RECORD
