Metadata-Version: 2.4
Name: trustcaptcha-python
Version: 1.2.1
Summary: (DEPRECATED)  TrustCaptcha for Python
Author-email: TrustComponent <mail@trustcomponent.com>
License: Apache-2.0
Project-URL: Homepage, https://www.trustcomponent.com/en/products/captcha/integrations/python-captcha
Project-URL: Replacement, https://pypi.org/project/trustcaptcha/
Keywords: captcha,gdpr,privacy,security,made-in-germany,eu,european-union
Classifier: Development Status :: 7 - Inactive
Classifier: Programming Language :: Python :: 3
License-File: LICENSE.md
Requires-Dist: requests
Requires-Dist: numpy
Provides-Extra: dev
Requires-Dist: pytest; extra == "dev"
Requires-Dist: flake8; extra == "dev"
Dynamic: license-file
